vokab/__init__.py
vokab/collection.py
vokab/config.py
vokab/const.py
vokab/entity.py
vokab/lazy.py
vokab/loader.py
vokab/logging.py
vokab/protocol.py
vokab/cli/__init__.py
vokab/cli/app.py
vokab/cli/eval.py
vokab/cli/init.py
vokab/cli/load.py
vokab/cli/reindex.py
vokab/databases/__init__.py
vokab/databases/abstract.py
vokab/databases/lancedb/__init__.py
vokab/databases/lancedb/database.py
vokab/databases/lancedb/entities.py
vokab/databases/lancedb/table.py
vokab/databases/lancedb/terms.py
vokab/databases/sqlite/__init__.py
vokab/databases/sqlite/database.py
vokab/databases/sqlite/sql/exact_search.sql
vokab/databases/sqlite/sql/fts_search.sql
vokab/databases/sqlite/sql/get_entity.sql
vokab/databases/sqlite/sql/init_tables.sql
vokab/databases/sqlite/sql/init_triggers.sql
vokab/databases/sqlite/sql/stats.sql
vokab/databases/sqlite/sql/upsert.sql
vokab/databases/sqlite/sql/vss_search.sql
vokab/encoders/__init__.py
vokab/encoders/abstract.py
vokab/encoders/sbert.py
vokab/fuzz/__init__.py
vokab/fuzz/abstract.py
vokab/fuzz/default.py
vokab/linkers/__init__.py
vokab/linkers/abstract.py
vokab/linkers/default.py
vokab/rerankers/__init__.py
vokab/rerankers/abstract.py
vokab/rerankers/rrf.py
vokab-0.0.2.dist-info/METADATA
vokab-0.0.2.dist-info/WHEEL
vokab-0.0.2.dist-info/entry_points.txt
vokab-0.0.2.dist-info/licenses/LICENSE
vokab-0.0.2.dist-info/RECORD
