Metadata-Version: 2.3
Name: vokab
Version: 0.0.2
Summary: vokab: named entity linking through hybrid (lexical and semantic) search engine.
Author-email: Ian Maurer <ian@genomoncology.com>
License-File: LICENSE
Classifier: Intended Audience :: Developers
Classifier: License :: OSI Approved :: MIT License
Classifier: Operating System :: OS Independent
Classifier: Programming Language :: Python :: 3
Classifier: Topic :: Software Development :: Libraries
Requires-Python: >=3.9
Requires-Dist: click>=8.0.0
Requires-Dist: pydantic>=2.6.1
Requires-Dist: rapidfuzz>=3.7.0
Requires-Dist: sentence-transformers>=2.2.2
Requires-Dist: streamlit>=1.33.0
Requires-Dist: torch>=2.2.2
Requires-Dist: tqdm
Provides-Extra: ext
Requires-Dist: aiosql>=10.1; extra == 'ext'
Requires-Dist: lancedb; extra == 'ext'
Requires-Dist: sqlite-vss; extra == 'ext'
Requires-Dist: tantivy; extra == 'ext'
Provides-Extra: local
Requires-Dist: build; extra == 'local'
Requires-Dist: ipython; extra == 'local'
Requires-Dist: pip; extra == 'local'
Requires-Dist: setuptools; extra == 'local'
Requires-Dist: twine; extra == 'local'
Provides-Extra: test
Requires-Dist: coverage[toml]; extra == 'test'
Requires-Dist: pytest; extra == 'test'
Requires-Dist: pytest-mock; extra == 'test'
